anonjail.py
anonjail-1.6.7.data/scripts/anonjail-install.bash
anonjail-1.6.7.dist-info/LICENSE.txt
anonjail-1.6.7.dist-info/METADATA
anonjail-1.6.7.dist-info/WHEEL
anonjail-1.6.7.dist-info/entry_points.txt
anonjail-1.6.7.dist-info/top_level.txt
anonjail-1.6.7.dist-info/RECORD
